flame_utils/__init__.py
flame_utils/core/__init__.py
flame_utils/core/element.py
flame_utils/core/model.py
flame_utils/core/state.py
flame_utils/io/__init__.py
flame_utils/io/lattice.py
flame_utils/io/output.py
flame_utils/misc/__init__.py
flame_utils/misc/alias.py
flame_utils/misc/confupdate.py
flame_utils/misc/listset.py
flame_utils/misc/machsetter.py
flame_utils/misc/message.py
flame_utils/viz/__init__.py
flame_utils/viz/plotlat.py
flame_utils-0.5.0.post1.dist-info/AUTHORS
flame_utils-0.5.0.post1.dist-info/LICENSE
flame_utils-0.5.0.post1.dist-info/METADATA
flame_utils-0.5.0.post1.dist-info/WHEEL
flame_utils-0.5.0.post1.dist-info/top_level.txt
flame_utils-0.5.0.post1.dist-info/RECORD
