Metadata-Version: 2.1
Name: flame-utils
Version: 0.5.0.post1
Summary: Utilities for FLAME Python interface
Home-page: https://github.com/frib-high-level-controls/flame-utils/
Author: Tong Zhang
Author-email: zhangt@frib.msu.edu
License: Copyright (c) 2017, Facility for Rare Isotope Beams
Requires-Dist: numpy
Requires-Dist: matplotlib
Requires-Dist: flame-code
